LICENSE
MANIFEST.in
README.md
requirements.txt
setup.cfg
setup.py
pygdebias/__init__.py
pygdebias.egg-info/PKG-INFO
pygdebias.egg-info/SOURCES.txt
pygdebias.egg-info/dependency_links.txt
pygdebias.egg-info/requires.txt
pygdebias.egg-info/top_level.txt
pygdebias/datasets/__init__.py
pygdebias/datasets/datasets.py
pygdebias/debiasing/CrossWalk.py
pygdebias/debiasing/EDITS.py
pygdebias/debiasing/FairEdit.py
pygdebias/debiasing/FairGNN.py
pygdebias/debiasing/FairVGNN.py
pygdebias/debiasing/FairWalk.py
pygdebias/debiasing/GEAR.py
pygdebias/debiasing/GNN.py
pygdebias/debiasing/GNN_cf.py
pygdebias/debiasing/GNN_individual.py
pygdebias/debiasing/GUIDE.py
pygdebias/debiasing/InFoRM_GNN.py
pygdebias/debiasing/NIFTY.py
pygdebias/debiasing/NIFTY_cf.py
pygdebias/debiasing/REDRESS.py
pygdebias/debiasing/RawlsGCN.py
pygdebias/debiasing/UGE.py
pygdebias/debiasing/__init__.py
pygdebias/metrics/__init__.py
pygdebias/metrics/metrics.py
pygdebias/tests/__init__.py
pygdebias/tests/test_data.py
pygdebias/tests/test_o.py