Metadata-Version: 2.1
Name: pygdebias
Version: 1.1.1
Summary: Attributed Network Datasets and Fairness-Aware Graph Mining Algorithms
Author: Yushun Dong, Song Wang, Zaiyi Zheng, Zhenyu Lei, Jing Ma, Chen Chen, Jundong Li
Author-email: yd6eb@virginia.edu
License: MIT
Classifier: License :: OSI Approved :: MIT License
Classifier: Programming Language :: Python :: 3.9
License-File: LICENSE
